inte_subject/__init__.py
inte_subject/action_items.py
inte_subject/admin_site.py
inte_subject/apps.py
inte_subject/baker_recipes.py
inte_subject/choices.py
inte_subject/constants.py
inte_subject/identifiers.py
inte_subject/urls.py
inte_subject/utils.py
inte_subject/admin/__init__.py
inte_subject/admin/health_economics_admin.py
inte_subject/admin/modeladmin.py
inte_subject/admin/subject_requisition_admin.py
inte_subject/admin/subject_visit_admin.py
inte_subject/admin/general_assessment/__init__.py
inte_subject/admin/general_assessment/anthropometry_admin.py
inte_subject/admin/general_assessment/diabetes_initial_review_admin.py
inte_subject/admin/general_assessment/general_assessment_admin.py
inte_subject/admin/general_assessment/general_assessment_initial_admin.py
inte_subject/admin/general_assessment/hiv_initial_review_admin.py
inte_subject/admin/general_assessment/hypertension_initial_review_admin.py
inte_subject/admin/general_assessment/physical_activity_admin.py
inte_subject/admin/general_assessment/risk_factors_admin.py
inte_subject/forms/__init__.py
inte_subject/forms/anthropometry_form.py
inte_subject/forms/diabetes_initial_review_form.py
inte_subject/forms/form_mixins.py
inte_subject/forms/general_assessment_form.py
inte_subject/forms/general_assessment_initial_form.py
inte_subject/forms/hiv_initial_review_form.py
inte_subject/forms/hypertension_initial_review_form.py
inte_subject/forms/physical_activity_form.py
inte_subject/forms/risk_factors_form.py
inte_subject/forms/subject_requisition_form.py
inte_subject/forms/subject_visit_form.py
inte_subject/migrations/0001_initial.py
inte_subject/migrations/0002_auto_20200202_1111.py
inte_subject/migrations/0003_auto_20200204_0939.py
inte_subject/migrations/0004_auto_20200204_1320.py
inte_subject/migrations/0005_auto_20200213_2055.py
inte_subject/migrations/__init__.py
inte_subject/model_mixins/__init__.py
inte_subject/model_mixins/search_slug_model_mixin.py
inte_subject/models/__init__.py
inte_subject-0.1.5.dist-info/AUTHORS
inte_subject-0.1.5.dist-info/LICENSE
inte_subject-0.1.5.dist-info/METADATA
inte_subject-0.1.5.dist-info/WHEEL
inte_subject-0.1.5.dist-info/top_level.txt
inte_subject-0.1.5.dist-info/RECORD
